oskaragent/__init__.py
oskaragent/agent.py
oskaragent/agent_config.py
oskaragent/agent_mcp_tools.py
oskaragent/agent_tools.py
oskaragent/helpers.py
oskaragent/converters/__init__.py
oskaragent/converters/csv_md.py
oskaragent/converters/docx_md.py
oskaragent/converters/helpers.py
oskaragent/converters/html_md.py
oskaragent/converters/json_csv.py
oskaragent/converters/json_md.py
oskaragent/converters/pdf_md.py
oskaragent/converters/pptx_md.py
oskaragent/rag/__init__.py
oskaragent/rag/faiss_kb.py
oskaragent/rag/file_renderers.py
oskaragent/rag/knowledgebase.py
oskaragent/rag/sql_repository.py
oskaragent-0.1.40.dist-info/licenses/LICENSE
oskaragent-0.1.40.dist-info/METADATA
oskaragent-0.1.40.dist-info/WHEEL
oskaragent-0.1.40.dist-info/top_level.txt
oskaragent-0.1.40.dist-info/RECORD
