Metadata-Version: 2.4
Name: oskaragent
Version: 0.1.40
Summary: Plataforma de agente conversacional Oskar.
Author: José Carlos Cordeiro
License-Expression: MIT
Requires-Python: >=3.10
License-File: LICENSE
Requires-Dist: openai==2.9.0
Requires-Dist: mcp==1.25.0
Requires-Dist: faiss-cpu==1.13.1
Requires-Dist: numpy==2.3.5
Requires-Dist: pandas==2.3.3
Requires-Dist: pyodbc==5.3.0
Requires-Dist: pyyaml==6.0.3
Requires-Dist: pypdf==6.4.1
Requires-Dist: pdfkit==1.0.0
Requires-Dist: pdfminer.six==20251107
Requires-Dist: python-docx==1.2.0
Requires-Dist: python-pptx==1.0.2
Requires-Dist: pillow==12.0.0
Requires-Dist: lxml==6.0.2
Requires-Dist: markdown2==2.5.4
Requires-Dist: beautifulsoup4==4.14.3
Requires-Dist: matplotlib==3.10.8
Requires-Dist: seaborn==0.13.2
Requires-Dist: tabulate==0.9.0
Requires-Dist: colorama==0.4.6
Dynamic: license-file
